INSTALL.txt
README.txt
setup.cfg
setup.py
Products/__init__.py
Products.PythonField.egg-info/PKG-INFO
Products.PythonField.egg-info/SOURCES.txt
Products.PythonField.egg-info/dependency_links.txt
Products.PythonField.egg-info/entry_points.txt
Products.PythonField.egg-info/namespace_packages.txt
Products.PythonField.egg-info/not-zip-safe
Products.PythonField.egg-info/requires.txt
Products.PythonField.egg-info/top_level.txt
Products/PythonField/CHANGES.txt
Products/PythonField/LICENSE.txt
Products/PythonField/README.txt
Products/PythonField/__init__.py
Products/PythonField/_field.py
Products/PythonField/validators.py
Products/PythonField/version.txt
Products/PythonField/tests/__init__.py
Products/PythonField/tests/framework.py
Products/PythonField/tests/runalltests.py
Products/PythonField/tests/test_field.py