Metadata-Version: 1.0
Name: Products.PythonField
Version: 1.1.3
Summary: Archetypes field for Python input
Home-page: http://plone.org/products/scriptablefields
Author: Jens Klein
Author-email: jens@bluedynamics.com
License: GPL
Keywords: Plone ScriptableFields PythonField
Platform: UNKNOWN
Classifier: Framework :: Plone
Classifier: Framework :: Zope2
Classifier: Programming Language :: Python
